MANIFEST.in
README.txt
setup.cfg
setup.py
docs/HISTORY.txt
raptus/__init__.py
raptus.googlemaps.egg-info/PKG-INFO
raptus.googlemaps.egg-info/SOURCES.txt
raptus.googlemaps.egg-info/dependency_links.txt
raptus.googlemaps.egg-info/entry_points.txt
raptus.googlemaps.egg-info/namespace_packages.txt
raptus.googlemaps.egg-info/not-zip-safe
raptus.googlemaps.egg-info/requires.txt
raptus.googlemaps.egg-info/top_level.txt
raptus/googlemaps/__init__.py
raptus/googlemaps/configure.zcml
raptus/googlemaps/browser/__init__.py
raptus/googlemaps/browser/configure.zcml
raptus/googlemaps/browser/googlemaps.js
raptus/googlemaps/profiles/default/jsregistry.xml
raptus/googlemaps/profiles/default/metadata.xml
raptus/googlemaps/profiles/default/skins.xml
raptus/googlemaps/skins/raptus_googlemaps/googlemaps_marker.png