Metadata-Version: 1.0
Name: raptus.googlemaps
Version: 1.0b8
Summary: Provides jQuery googlemaps plugin and handles api keys
Home-page: http://raptus.com
Author: Raptus AG
Author-email: dev@raptus.com
License: GPL
Platform: UNKNOWN
Classifier: Programming Language :: Python
Classifier: Topic :: Software Development :: Libraries :: Python Modules
